django_bank_requisites/__init__.py
django_bank_requisites/base_validators.py
django_bank_requisites/django_validators.py
django_bank_requisites/exception_handler.py
django_bank_requisites/mixins.py
django_bank_requisites/models.py
django_bank_requisites/serializers.py
tests/__init__.py
tests/test_base_validators.py
django_bank_requisites-0.1.0.dist-info/LICENSE
django_bank_requisites-0.1.0.dist-info/METADATA
django_bank_requisites-0.1.0.dist-info/WHEEL
django_bank_requisites-0.1.0.dist-info/top_level.txt
django_bank_requisites-0.1.0.dist-info/RECORD
